h5mapper/__init__.py
h5mapper/core.py
h5mapper/create.py
h5mapper/crud.py
h5mapper/features.py
h5mapper/file_walker.py
h5mapper/serve.py
h5mapper/utils.py
h5mapper-0.3.3.dist-info/METADATA
h5mapper-0.3.3.dist-info/WHEEL
h5mapper-0.3.3.dist-info/entry_points.txt
h5mapper-0.3.3.dist-info/licenses/LICENSE
h5mapper-0.3.3.dist-info/RECORD
