Metadata-Version: 2.4
Name: h5mapper
Version: 0.3.3
Summary: pythonic ORM tool for reading and writing HDF5 data
Project-URL: Download, https://github.com/ktonal/h5mapper
Project-URL: Homepage, https://github.com/ktonal/h5mapper
Author-email: Antoine Daurat <antoinedaurat@gmail.com>
License-Expression: MIT
License-File: LICENSE
Keywords: ORM,deep-learning,h5py,hdf5,machine-learning
Classifier: Development Status :: 3 - Alpha
Classifier: Intended Audience :: Developers
Classifier: Intended Audience :: Other Audience
Classifier: Intended Audience :: Science/Research
Classifier: License :: OSI Approved :: GNU General Public License v3 (GPLv3)
Classifier: Programming Language :: Python :: 3.10
Classifier: Programming Language :: Python :: 3.11
Classifier: Programming Language :: Python :: 3.12
Requires-Python: >=3.10
Requires-Dist: dill
Requires-Dist: h5py>=3.0.0
Requires-Dist: ipython
Requires-Dist: multiprocess
Requires-Dist: numpy<2,>=1.19.0
Requires-Dist: torch>=2.0.0
Requires-Dist: tqdm
